{"nodes": [{"id": "voice_triage_skill", "label": "sre-voice-triage Skill", "file_type": "document", "source_file": "skills/sre/voice-triage/SKILL.md", "source_location": null, "source_url": null, "captured_at": null, "author": "AIOps SRE Agent", "contributor": null}], "edges": [{"source": "voice_triage_skill", "target": "investigate_skill", "relation": "references", "confidence": "EXTRACTED", "confidence_score": 1, "source_file": "skills/sre/voice-triage/SKILL.md", "source_location": null, "weight": 1}, {"source": "voice_triage_skill", "target": "architecture_alert_webhook_flow", "relation": "conceptually_related_to", "confidence": "INFERRED", "confidence_score": 0.68, "source_file": "skills/sre/voice-triage/SKILL.md", "source_location": null, "weight": 1}], "hyperedges": []}