{"nodes": [{"id": "home_mao_aiops_tests_conftest_py", "label": "conftest.py", "file_type": "code", "source_file": "/home/mao/aiops/tests/conftest.py", "source_location": "L1"}, {"id": "tests_conftest_pytest_configure", "label": "pytest_configure()", "file_type": "code", "source_file": "/home/mao/aiops/tests/conftest.py", "source_location": "L15"}, {"id": "tests_conftest_pytest_pyfunc_call", "label": "pytest_pyfunc_call()", "file_type": "code", "source_file": "/home/mao/aiops/tests/conftest.py", "source_location": "L20"}, {"id": "tests_conftest_rationale_21", "label": "\u5728\u672a\u5b89\u88c5 pytest-asyncio \u65f6\u8fd0\u884c async \u6d4b\u8bd5\u51fd\u6570\u3002", "file_type": "rationale", "source_file": "/home/mao/aiops/tests/conftest.py", "source_location": "L21"}], "edges": [{"source": "home_mao_aiops_tests_conftest_py", "target": "asyncio", "relation": "imports", "context": "import", "confidence": "EXTRACTED", "source_file": "/home/mao/aiops/tests/conftest.py", "source_location": "L5", "weight": 1.0}, {"source": "home_mao_aiops_tests_conftest_py", "target": "inspect", "relation": "imports", "context": "import", "confidence": "EXTRACTED", "source_file": "/home/mao/aiops/tests/conftest.py", "source_location": "L6", "weight": 1.0}, {"source": "home_mao_aiops_tests_conftest_py", "target": "sys", "relation": "imports", "context": "import", "confidence": "EXTRACTED", "source_file": "/home/mao/aiops/tests/conftest.py", "source_location": "L7", "weight": 1.0}, {"source": "home_mao_aiops_tests_conftest_py", "target": "pathlib", "relation": "imports_from", "context": "import", "confidence": "EXTRACTED", "source_file": "/home/mao/aiops/tests/conftest.py", "source_location": "L8", "weight": 1.0}, {"source": "home_mao_aiops_tests_conftest_py", "target": "tests_conftest_pytest_configure", "relation": "contains", "confidence": "EXTRACTED", "source_file": "/home/mao/aiops/tests/conftest.py", "source_location": "L15", "weight": 1.0}, {"source": "home_mao_aiops_tests_conftest_py", "target": "tests_conftest_pytest_pyfunc_call", "relation": "contains", "confidence": "EXTRACTED", "source_file": "/home/mao/aiops/tests/conftest.py", "source_location": "L20", "weight": 1.0}, {"source": "tests_conftest_rationale_21", "target": "tests_conftest_pytest_pyfunc_call", "relation": "rationale_for", "confidence": "EXTRACTED", "source_file": "/home/mao/aiops/tests/conftest.py", "source_location": "L21", "weight": 1.0}], "raw_calls": [{"caller_nid": "tests_conftest_pytest_configure", "callee": "addinivalue_line", "is_member_call": true, "source_file": "/home/mao/aiops/tests/conftest.py", "source_location": "L17"}, {"caller_nid": "tests_conftest_pytest_pyfunc_call", "callee": "iscoroutinefunction", "is_member_call": true, "source_file": "/home/mao/aiops/tests/conftest.py", "source_location": "L23"}, {"caller_nid": "tests_conftest_pytest_pyfunc_call", "callee": "run", "is_member_call": true, "source_file": "/home/mao/aiops/tests/conftest.py", "source_location": "L26"}, {"caller_nid": "tests_conftest_pytest_pyfunc_call", "callee": "test_func", "is_member_call": false, "source_file": "/home/mao/aiops/tests/conftest.py", "source_location": "L26"}]}